xtrail_ai/__init__.py
xtrail_ai/api.py
xtrail_ai/machine_id.py
xtrail_ai/utils.py
xtrail_ai-0.4.dist-info/METADATA
xtrail_ai-0.4.dist-info/WHEEL
xtrail_ai-0.4.dist-info/top_level.txt
xtrail_ai-0.4.dist-info/RECORD
